aisquared/__init__.py
aisquared/base/BaseObject.py
aisquared/base/__init__.py
aisquared/base/css.py
aisquared/base/endpoints.py
aisquared/base/harvesting.py
aisquared/base/platform.py
aisquared/base/preprocessing.py
aisquared/base/rendering.py
aisquared/base/stages.py
aisquared/config/CustomObject.py
aisquared/config/GraphConfiguration.py
aisquared/config/ModelConfiguration.py
aisquared/config/__init__.py
aisquared/config/analytic/DeployedAnalytic.py
aisquared/config/analytic/DeployedModel.py
aisquared/config/analytic/LocalAnalytic.py
aisquared/config/analytic/LocalModel.py
aisquared/config/analytic/OnnxModel.py
aisquared/config/analytic/ReverseMLWorkflow.py
aisquared/config/analytic/__init__.py
aisquared/config/feedback/BinaryFeedback.py
aisquared/config/feedback/ModelFeedback.py
aisquared/config/feedback/MulticlassFeedback.py
aisquared/config/feedback/QualitativeFeedback.py
aisquared/config/feedback/RegressionFeedback.py
aisquared/config/feedback/SimpleFeedback.py
aisquared/config/feedback/__init__.py
aisquared/config/harvesting/ChatbotHarvester.py
aisquared/config/harvesting/ImageHarvester.py
aisquared/config/harvesting/InputHarvester.py
aisquared/config/harvesting/QueryParameterHarvester.py
aisquared/config/harvesting/TextHarvester.py
aisquared/config/harvesting/__init__.py
aisquared/config/postprocessing/BinaryClassification.py
aisquared/config/postprocessing/MulticlassClassification.py
aisquared/config/postprocessing/ObjectDetection.py
aisquared/config/postprocessing/Regression.py
aisquared/config/postprocessing/__init__.py
aisquared/config/preprocessing/__init__.py
aisquared/config/preprocessing/image/ImagePreprocessing.py
aisquared/config/preprocessing/image/Steps.py
aisquared/config/preprocessing/image/__init__.py
aisquared/config/preprocessing/tabular/Steps.py
aisquared/config/preprocessing/tabular/TabularPreprocessing.py
aisquared/config/preprocessing/tabular/__init__.py
aisquared/config/preprocessing/text/Steps.py
aisquared-0.3.13.dist-info/METADATA
aisquared-0.3.13.dist-info/WHEEL
aisquared-0.3.13.dist-info/top_level.txt
aisquared-0.3.13.dist-info/RECORD
