Metadata-Version: 2.1
Name: aisquared
Version: 0.3.13
Summary: Utilities for interacting with the AI Squared Technology Stack
Home-page: https://github.com/AISquaredInc/aisquared
Author: The AI Squared Team
Author-email: staff@squared.ai
License: Apache 2.0
Requires-Dist: numpy
Requires-Dist: pandas
Provides-Extra: full
Requires-Dist: mlflow ; extra == 'full'
Requires-Dist: flask ; extra == 'full'
Requires-Dist: waitress ; extra == 'full'
Requires-Dist: click ; extra == 'full'
Requires-Dist: beyondml ; extra == 'full'
Requires-Dist: scikit-learn ; extra == 'full'
Requires-Dist: torch ; extra == 'full'
Requires-Dist: llmlink ; extra == 'full'
Requires-Dist: tensorflowjs ; extra == 'full'
Requires-Dist: tensorflow ; extra == 'full'
